actrisk/__init__.py
actrisk/config.yaml
actrisk/core/__init__.py
actrisk/core/actfitter.py
actrisk/core/actsimulator.py
actrisk/tools/__init__.py
actrisk/tools/claimsimulator.py
actrisk/utils/__init__.py
actrisk/utils/utils.py
actrisk-0.1.0.6.dist-info/licenses/LICENSE
actrisk-0.1.0.6.dist-info/METADATA
actrisk-0.1.0.6.dist-info/WHEEL
actrisk-0.1.0.6.dist-info/top_level.txt
actrisk-0.1.0.6.dist-info/RECORD
