Metadata-Version: 2.4
Name: actrisk
Version: 0.1.0.6
Summary: Of the Actuary, By the Actuary, For the Actuary: A ZNSTARS Python package for actuarial risk modeling and simulation
Author: Juntao Zhang
Author-email: jzhng106@gmail.com
License: Apache License 2.0
Project-URL: Homepage, https://github.com/jzhng105/actrisk
Project-URL: Documentation, https://github.com/jzhng105/actrisk/docs
Requires-Python: >=3.8
License-File: LICENSE
Requires-Dist: numpy>=1.26
Requires-Dist: scipy>=1.7
Requires-Dist: pandas>=1.3
Requires-Dist: matplotlib>=3.4
Requires-Dist: actstats>=0.1.1
Requires-Dist: seaborn>=0.13.2
Dynamic: license-file
